{
  "generator-jhipster": {
    "promptValues": {
      "packageName": "br.inforsystem"
    },
    "jhipsterVersion": "4.14.3",
    "baseName": "inforsystem",
    "packageName": "br.inforsystem",
    "packageFolder": "br/inforsystem",
    "serverPort": "8080",
    "authenticationType": "jwt",
    "cacheProvider": "ehcache",
    "enableHibernateCache": true,
    "websocket": false,
    "databaseType": "sql",
    "devDatabaseType": "mysql",
    "prodDatabaseType": "mysql",
    "searchEngine": false,
    "messageBroker": false,
    "serviceDiscoveryType": "eureka",
    "buildTool": "maven",
    "enableSocialSignIn": false,
    "enableSwaggerCodegen": false,
    "jwtSecretKey": "7ad9f4cbdec62e211fbf2f67c66916b9c6e664fe",
    "clientFramework": "angular1",
    "useSass": false,
    "clientPackageManager": "npm",
    "applicationType": "monolith",
    "testFrameworks": [],
    "jhiPrefix": "jhi",
    "enableTranslation": false
  }
}